{"mID":490600425,"lobbyType":"Normal Matchmaking","gameMode":"All Pick","region":"SE Asia","duration":"00:11:20","radiantVictory":false,"timestamp":"Jan 30, 2014 5:23:19 AM","players":[{"player":"Anonymous","pID":0,"heroName":"natures-prophet","lvl":6,"kills":2,"deaths":3,"assists":0,"gold":3800,"lastHits":31,"denies":0,"XPM":179,"GPM":334,"HD":1600,"HH":0,"TD":0,"radiant":true,"itemBuild":["ring-of-basilius","hand-of-midas","boots-of-speed"]},{"player":"Anonymous","pID":0,"heroName":"terrorblade","lvl":9,"kills":3,"deaths":4,"assists":2,"gold":4200,"lastHits":18,"denies":0,"XPM":472,"GPM":368,"HD":4400,"HH":0,"TD":0,"radiant":true,"itemBuild":["quelling-blade","wraith-band","tango","iron-branch","town-portal-scroll","power-treads"]},{"player":"Leviathan","pID":100272411,"heroName":"lina","lvl":8,"kills":4,"deaths":3,"assists":2,"gold":4100,"lastHits":8,"denies":0,"XPM":313,"GPM":364,"HD":5700,"HH":0,"TD":0,"radiant":true,"itemBuild":["magic-wand","bottle","boots-of-speed","null-talisman","town-portal-scroll"]},{"player":"Anonymous","pID":0,"heroName":"dragon-knight","lvl":3,"kills":0,"deaths":1,"assists":0,"gold":1600,"lastHits":6,"denies":0,"XPM":55,"GPM":138,"HD":451,"HH":0,"TD":0,"radiant":true,"itemBuild":["stout-shield","gauntlets-of-strength","iron-branch"]},{"player":"Anonymous","pID":0,"heroName":"doom","lvl":4,"kills":0,"deaths":0,"assists":0,"gold":1700,"lastHits":6,"denies":0,"XPM":94,"GPM":154,"HD":577,"HH":0,"TD":0,"radiant":true,"itemBuild":[]},{"player":"Anonymous","pID":0,"heroName":"ogre-magi","lvl":7,"kills":1,"deaths":2,"assists":2,"gold":2700,"lastHits":8,"denies":1,"XPM":232,"GPM":238,"HD":672,"HH":0,"TD":210,"radiant":false,"itemBuild":["town-portal-scroll","headdress","arcane-boots"]},{"player":"?Ghost","pID":151278773,"heroName":"luna","lvl":7,"kills":0,"deaths":4,"assists":7,"gold":3000,"lastHits":15,"denies":2,"XPM":276,"GPM":266,"HD":2900,"HH":0,"TD":487,"radiant":false,"itemBuild":["magic-wand","poor-mans-shield","boots-of-speed","ring-of-basilius","clarity"]},{"player":"Anonymous","pID":0,"heroName":"puck","lvl":9,"kills":3,"deaths":0,"assists":3,"gold":4100,"lastHits":25,"denies":1,"XPM":440,"GPM":358,"HD":2900,"HH":0,"TD":177,"radiant":false,"itemBuild":["arcane-boots","tango","iron-branch","iron-branch"]},{"player":"Anonymous","pID":0,"heroName":"bloodseeker","lvl":9,"kills":4,"deaths":1,"assists":2,"gold":4500,"lastHits":40,"denies":10,"XPM":426,"GPM":397,"HD":3500,"HH":0,"TD":335,"radiant":false,"itemBuild":["phase-boots","tango","quelling-blade","stout-shield","staff-of-wizardry","null-talisman"]},{"player":"Anonymous","pID":0,"heroName":"pudge","lvl":6,"kills":2,"deaths":3,"assists":1,"gold":2900,"lastHits":14,"denies":0,"XPM":222,"GPM":257,"HD":1800,"HH":0,"TD":188,"radiant":false,"itemBuild":["hood-of-defiance","tango","boots-of-speed"]}]}