{"mID":490600241,"lobbyType":"Ranked Matchmaking","gameMode":"All Pick","region":"South America","duration":"00:37:42","radiantVictory":false,"timestamp":"Jan 30, 2014 5:49:13 AM","players":[{"player":"?????","pID":42702707,"heroName":"clinkz","lvl":13,"kills":5,"deaths":5,"assists":6,"gold":9700,"lastHits":56,"denies":6,"XPM":241,"GPM":256,"HD":9400,"HH":0,"TD":826,"radiant":true,"itemBuild":["orchid-malevolence","magic-wand","ring-of-aquila","power-treads","javelin"]},{"player":"? Load :$","pID":40060616,"heroName":"earth-spirit","lvl":11,"kills":1,"deaths":10,"assists":12,"gold":7200,"lastHits":30,"denies":2,"XPM":206,"GPM":190,"HD":6400,"HH":357,"TD":258,"radiant":true,"itemBuild":["urn-of-shadows","magic-wand","arcane-boots","stout-shield","town-portal-scroll","bracer"]},{"player":"BcL\u0027 budweiser","pID":101886996,"heroName":"shadow-fiend","lvl":17,"kills":8,"deaths":8,"assists":6,"gold":15500,"lastHits":140,"denies":20,"XPM":441,"GPM":412,"HD":12700,"HH":0,"TD":677,"radiant":true,"itemBuild":["black-king-bar","bottle","desolator","power-treads","slippers-of-agility"]},{"player":"Psych0S1d","pID":54721935,"heroName":"witch-doctor","lvl":12,"kills":3,"deaths":11,"assists":9,"gold":7900,"lastHits":20,"denies":0,"XPM":236,"GPM":209,"HD":7700,"HH":218,"TD":214,"radiant":true,"itemBuild":["arcane-boots","buckler","ring-of-basilius","bracer","headdress","observer-ward"]},{"player":"Anonymous","pID":0,"heroName":"vengeful-spirit","lvl":14,"kills":1,"deaths":10,"assists":8,"gold":8400,"lastHits":50,"denies":2,"XPM":277,"GPM":224,"HD":5600,"HH":0,"TD":373,"radiant":true,"itemBuild":["sange-and-yasha","phase-boots","iron-branch","gauntlets-of-strength"]},{"player":"Anonymous","pID":0,"heroName":"terrorblade","lvl":19,"kills":17,"deaths":3,"assists":6,"gold":20600,"lastHits":93,"denies":0,"XPM":545,"GPM":547,"HD":10200,"HH":0,"TD":9300,"radiant":false,"itemBuild":["manta-style","power-treads","orb-of-venom","sange-and-yasha","helm-of-the-dominator","gem-of-true-sight"]},{"player":"xT.Otter","pID":41695112,"heroName":"lich","lvl":18,"kills":6,"deaths":1,"assists":17,"gold":13700,"lastHits":28,"denies":1,"XPM":481,"GPM":364,"HD":14400,"HH":0,"TD":365,"radiant":false,"itemBuild":["aghanims-scepter","bracer","tranquil-boots","vitality-booster"]},{"player":"Anonymous","pID":0,"heroName":"huskar","lvl":18,"kills":5,"deaths":8,"assists":16,"gold":14800,"lastHits":74,"denies":1,"XPM":453,"GPM":393,"HD":10800,"HH":995,"TD":1100,"radiant":false,"itemBuild":["armlet-of-mordiggian","urn-of-shadows","black-king-bar","iron-branch","power-treads"]},{"player":"Anonymous","pID":0,"heroName":"timbersaw","lvl":20,"kills":14,"deaths":2,"assists":10,"gold":21100,"lastHits":173,"denies":6,"XPM":609,"GPM":560,"HD":14300,"HH":1000,"TD":428,"radiant":false,"itemBuild":["ghost-scepter","boots-of-travel","blade-mail","bloodstone","heart-of-tarrasque","hood-of-defiance"]},{"player":"Anonymous","pID":0,"heroName":"crystal-maiden","lvl":14,"kills":2,"deaths":5,"assists":11,"gold":10900,"lastHits":48,"denies":0,"XPM":295,"GPM":288,"HD":4700,"HH":0,"TD":488,"radiant":false,"itemBuild":["aghanims-scepter","tranquil-boots","dust-of-appearance","sentry-ward","observer-ward"]}]}